asu_theory_of_cs/__init__.py
asu_theory_of_cs/automata/__init__.py
asu_theory_of_cs/automata/base.py
asu_theory_of_cs/automata/dfa.py
asu_theory_of_cs/automata/dfa_old.py
asu_theory_of_cs/automata/nfa.py
asu_theory_of_cs/errors/__init__.py
asu_theory_of_cs/registry/__init__.py
asu_theory_of_cs/util/__init__.py
asu_theory_of_cs-0.1.1.dist-info/METADATA
asu_theory_of_cs-0.1.1.dist-info/WHEEL
asu_theory_of_cs-0.1.1.dist-info/RECORD
